ktf/__init__.py
ktf/engine.py
ktf/env.py
ktf/ktf.py
ktf/run_tests.py
ktf/server.py
ktf-0.1.5.data/scripts/ktf
ktf-0.1.5.dist-info/AUTHORS
ktf-0.1.5.dist-info/LICENSE
ktf-0.1.5.dist-info/METADATA
ktf-0.1.5.dist-info/WHEEL
ktf-0.1.5.dist-info/top_level.txt
ktf-0.1.5.dist-info/RECORD
